{
    "ServiceURL": "https://dataservice.iifl.in/openapi/prod/",
    "AppName": "IIFLMarSHUBHAMR",
    "AppVer": "1.0",
    "Key": "ThG6LZT8JJUWi5mD8OMHYTdsOmFzkebF",
    "OsName": "Android",
    "RequestCode": "IIFLMarRQLoginForVendor",
    "RequestCodeHoldingV2": "IIFLMarRQHoldingV2",
    "RequestCodeMarketFeed": "IIFLMarRQMarketFeed",
    "RequestCodeOrdReq": "IIFLMarRQOrdReq",
    "RequestCodeOrdStatus": "IIFLMarRQOrdStatus",
    "RequestCodeTrdInfo":"IIFLMarRQTrdInfo",
    "UserID": "38wqMxgHEaM",
    "Password": "iRwx6yEij41",
    "VersionNo":"1.0.16.0",
    "OcpKey":"fc714d8e5b82438a93a95baa493ff45b"
}